STMGraph_pyG0/STMGraph.py
STMGraph_pyG0/Train_STMGraph.py
STMGraph_pyG0/__init__.py
STMGraph_pyG0/gat_conv.py
STMGraph_pyG0/gatv2_conv.py
STMGraph_pyG0/utils.py
stmgraph_pyg-0.0.1.dist-info/LICENSE.txt
stmgraph_pyg-0.0.1.dist-info/METADATA
stmgraph_pyg-0.0.1.dist-info/WHEEL
stmgraph_pyg-0.0.1.dist-info/top_level.txt
stmgraph_pyg-0.0.1.dist-info/RECORD
