Metadata-Version: 2.1
Name: STMGraph_pyG
Version: 0.0.1
Summary: A spatial-context-aware of spatial transcriptomes package
Author-email: Lixian Lin <llx_1910@163.com>
Project-URL: Homepage, https://github.com/binbin_coder/STMGraph_pyg
Project-URL: Bug Tracker, https://github.com/binbin_coder/STMGraph_pyg/issues
Classifier: Programming Language :: Python :: 3
Classifier: License :: OSI Approved :: MIT License
Classifier: Operating System :: OS Independent
Requires-Python: >=3.9
License-File: LICENSE.txt
